execdir/__init__.py
execdir/zkSync.py
zkSync-0.1.1.dist-info/DESCRIPTION.rst
zkSync-0.1.1.dist-info/METADATA
zkSync-0.1.1.dist-info/RECORD
zkSync-0.1.1.dist-info/WHEEL
zkSync-0.1.1.dist-info/entry_points.txt
zkSync-0.1.1.dist-info/metadata.json
zkSync-0.1.1.dist-info/top_level.txt
