Metadata-Version: 2.0
Name: zkSync
Version: 0.1.1
Summary: Copy zk data from one node to another node
Home-page: UNKNOWN
Author: dvsv2
Author-email: dvsv2@foxmail.com
License: UNKNOWN
Keywords: zookeeper sync zk zkSync
Platform: UNKNOWN
Requires-Dist: kazoo
Requires-Dist: logging
